[
    {
        "id": "1",
        "headline": "Goede service, lekker eten, toffe ambiance",
        "sliderText": "Lorem ipsum dolor sit amet, consetetur sadipscing elitr, sed diam nonumy eirmod tempor invidunt ut labore et dolore magna aliquyam erat, sed diam voluptua. At vero eos et accusam et justo duo  dolores et ea rebum. Stet clita kasd gubergren.",
        "author": "ALAIN HEYNDRICKX"
    },
    {
        "id": "2",
        "headline": "Goede service, lekker eten, toffe ambiance",
        "sliderText": "Lorem ipsum dolor sit amet, consetetur sadipscing elitr, sed diam nonumy eirmod tempor invidunt ut labore et dolore magna aliquyam erat, sed diam voluptua. At vero eos et accusam et justo duo  dolores et ea rebum. Stet clita kasd gubergren.",
        "author": "ALAIN HEYNDRICKX"
    }
]